capital_com_mcp_server/__init__.py
capital_com_mcp_server/capital_client.py
capital_com_mcp_server/capital_mcp_server.py
capital_com_mcp_server-0.3.2.dist-info/METADATA
capital_com_mcp_server-0.3.2.dist-info/WHEEL
capital_com_mcp_server-0.3.2.dist-info/entry_points.txt
capital_com_mcp_server-0.3.2.dist-info/licenses/LICENSE
capital_com_mcp_server-0.3.2.dist-info/RECORD
