Metadata-Version: 2.4
Name: capital-com-mcp-server
Version: 0.3.2
Summary: Capital.com MCP Server for Amazon Q and other LLMs
Project-URL: Homepage, https://github.com/syedair/mcp-servers
Project-URL: Bug Tracker, https://github.com/syedair/mcp-servers/issues
Author-email: Syed Humair <your.email@example.com>
License: MIT
License-File: LICENSE
Classifier: License :: OSI Approved :: MIT License
Classifier: Operating System :: OS Independent
Classifier: Programming Language :: Python :: 3
Requires-Python: >=3.10
Requires-Dist: fastmcp>=0.1.0
Requires-Dist: pydantic>=2.0.0
Requires-Dist: requests>=2.25.0
